stringstandardization/__init__.py
stringstandardization/stringstd.py
devopsstringprocess-0.0.2.dist-info/LICENSE
devopsstringprocess-0.0.2.dist-info/METADATA
devopsstringprocess-0.0.2.dist-info/WHEEL
devopsstringprocess-0.0.2.dist-info/top_level.txt
devopsstringprocess-0.0.2.dist-info/RECORD
